[
	{
		"rank": 1,
		"name": "Dejairzin",
		"vocation": "Elder Druid",
		"world": "Inabra",
		"level": 2990,
		"value": 444667644179
	},
	{
		"rank": 2,
		"name": "Bobeek",
		"vocation": "Elder Druid",
		"world": "Bona",
		"level": 2953,
		"value": 428425356817
	},
	{
		"rank": 3,
		"name": "Goraca",
		"vocation": "Master Sorcerer",
		"world": "Bona",
		"level": 2950,
		"value": 427013451606
	},
	{
		"rank": 4,
		"name": "Veyllor",
		"vocation": "Royal Paladin",
		"world": "Gentebra",
		"level": 2907,
		"value": 408769261259
	},
	{
		"rank": 5,
		"name": "Warlord Teuzin",
		"vocation": "Master Sorcerer",
		"world": "Belobra",
		"level": 2871,
		"value": 393936958800
	},
	{
		"rank": 6,
		"name": "Vepeh",
		"vocation": "Royal Paladin",
		"world": "Celebra",
		"level": 2855,
		"value": 387269497850
	},
	{
		"rank": 7,
		"name": "Mago Morto",
		"vocation": "Master Sorcerer",
		"world": "Celebra",
		"level": 2793,
		"value": 362518035784
	},
	{
		"rank": 8,
		"name": "Kommander",
		"vocation": "Royal Paladin",
		"world": "Celebra",
		"level": 2786,
		"value": 359680010310
	},
	{
		"rank": 9,
		"name": "Warlord Leonny",
		"vocation": "Royal Paladin",
		"world": "Belobra",
		"level": 2778,
		"value": 356658373031
	},
	{
		"rank": 10,
		"name": "Ke vinho",
		"vocation": "Elder Druid",
		"world": "Gentebra",
		"level": 2778,
		"value": 356548705910
	},
	{
		"rank": 11,
		"name": "Warlord Bread",
		"vocation": "Elder Druid",
		"world": "Belobra",
		"level": 2776,
		"value": 355990740700
	},
	{
		"rank": 12,
		"name": "Baaeck",
		"vocation": "Master Sorcerer",
		"world": "Gentebra",
		"level": 2709,
		"value": 330771474690
	},
	{
		"rank": 13,
		"name": "Galll",
		"vocation": "Elite Knight",
		"world": "Gentebra",
		"level": 2703,
		"value": 328629568864
	},
	{
		"rank": 14,
		"name": "Izzy The Beast",
		"vocation": "Elder Druid",
		"world": "Celebra",
		"level": 2671,
		"value": 317067177352
	},
	{
		"rank": 15,
		"name": "Szimix",
		"vocation": "Elder Druid",
		"world": "Celesta",
		"level": 2626,
		"value": 301394798191
	},
	{
		"rank": 16,
		"name": "Teus",
		"vocation": "Master Sorcerer",
		"world": "Descubra",
		"level": 2615,
		"value": 297363560919
	},
	{
		"rank": 17,
		"name": "Ferangel",
		"vocation": "Royal Paladin",
		"world": "Bona",
		"level": 2579,
		"value": 285242095746
	},
	{
		"rank": 18,
		"name": "Khaos Poderoso",
		"vocation": "Master Sorcerer",
		"world": "Unebra",
		"level": 2575,
		"value": 284156424633
	},
	{
		"rank": 19,
		"name": "Marcao Implacavel",
		"vocation": "Elder Druid",
		"world": "Kalibra",
		"level": 2561,
		"value": 279461762270
	},
	{
		"rank": 20,
		"name": "Elder Reno",
		"vocation": "Elder Druid",
		"world": "Celesta",
		"level": 2520,
		"value": 266302465526
	},
	{
		"rank": 21,
		"name": "Ki Naitao Olim",
		"vocation": "Elite Knight",
		"world": "Belobra",
		"level": 2517,
		"value": 265200961229
	},
	{
		"rank": 22,
		"name": "Joseh Implacavel",
		"vocation": "Royal Paladin",
		"world": "Kalibra",
		"level": 2514,
		"value": 264389408319
	},
	{
		"rank": 23,
		"name": "Sephan",
		"vocation": "Elite Knight",
		"world": "Celebra",
		"level": 2506,
		"value": 261670570482
	},
	{
		"rank": 24,
		"name": "Boleight",
		"vocation": "Royal Paladin",
		"world": "Descubra",
		"level": 2504,
		"value": 261058496305
	},
	{
		"rank": 25,
		"name": "Ma rkin",
		"vocation": "Elder Druid",
		"world": "Descubra",
		"level": 2474,
		"value": 251983503768
	},
	{
		"rank": 26,
		"name": "Mazzeriin",
		"vocation": "Royal Paladin",
		"world": "Karmeya",
		"level": 2456,
		"value": 246418865480
	},
	{
		"rank": 27,
		"name": "Poke Corporation",
		"vocation": "Royal Paladin",
		"world": "Issobra",
		"level": 2455,
		"value": 246285118759
	},
	{
		"rank": 28,
		"name": "Guii",
		"vocation": "Elite Knight",
		"world": "Celebra",
		"level": 2454,
		"value": 245802081475
	},
	{
		"rank": 29,
		"name": "King Danter",
		"vocation": "Elite Knight",
		"world": "Celesta",
		"level": 2451,
		"value": 244841370917
	},
	{
		"rank": 30,
		"name": "Machamp Jiujitsu",
		"vocation": "Master Sorcerer",
		"world": "Lobera",
		"level": 2442,
		"value": 242285882446
	},
	{
		"rank": 31,
		"name": "Maqiczny",
		"vocation": "Elite Knight",
		"world": "Refugia",
		"level": 2435,
		"value": 240207008749
	},
	{
		"rank": 32,
		"name": "Gutierrezs",
		"vocation": "Elder Druid",
		"world": "Gentebra",
		"level": 2426,
		"value": 237474471428
	},
	{
		"rank": 33,
		"name": "Uhaacz",
		"vocation": "Elder Druid",
		"world": "Karmeya",
		"level": 2418,
		"value": 235316798326
	},
	{
		"rank": 34,
		"name": "Rayo",
		"vocation": "Royal Paladin",
		"world": "Gentebra",
		"level": 2417,
		"value": 234948158138
	},
	{
		"rank": 35,
		"name": "Caffeina Implacavel",
		"vocation": "Master Sorcerer",
		"world": "Kalibra",
		"level": 2411,
		"value": 233234534455
	},
	{
		"rank": 36,
		"name": "Drackule",
		"vocation": "Elder Druid",
		"world": "Refugia",
		"level": 2406,
		"value": 231802204731
	},
	{
		"rank": 37,
		"name": "Vinyzz",
		"vocation": "Elite Knight",
		"world": "Nefera",
		"level": 2402,
		"value": 230485722020
	},
	{
		"rank": 38,
		"name": "Dudopix Worldwide",
		"vocation": "Elite Knight",
		"world": "Ferobra",
		"level": 2398,
		"value": 229273920163
	},
	{
		"rank": 39,
		"name": "Edinho Rancaprofit",
		"vocation": "Royal Paladin",
		"world": "Serdebra",
		"level": 2390,
		"value": 227160046934
	},
	{
		"rank": 40,
		"name": "Digao Implacavel",
		"vocation": "Elite Knight",
		"world": "Kalibra",
		"level": 2389,
		"value": 226740537431
	},
	{
		"rank": 41,
		"name": "Vengelz",
		"vocation": "Elite Knight",
		"world": "Descubra",
		"level": 2383,
		"value": 224997490856
	},
	{
		"rank": 42,
		"name": "Bruneli Wayne",
		"vocation": "Elite Knight",
		"world": "Serdebra",
		"level": 2381,
		"value": 224479382889
	},
	{
		"rank": 43,
		"name": "Hero Reis",
		"vocation": "Royal Paladin",
		"world": "Astera",
		"level": 2380,
		"value": 224359299766
	},
	{
		"rank": 44,
		"name": "Nevropz Toxico",
		"vocation": "Elder Druid",
		"world": "Kalibra",
		"level": 2378,
		"value": 223735633883
	},
	{
		"rank": 45,
		"name": "Pedrin Descongelou",
		"vocation": "Elder Druid",
		"world": "Jadebra",
		"level": 2376,
		"value": 223182431603
	},
	{
		"rank": 46,
		"name": "Bomba Chapeleiro",
		"vocation": "Elite Knight",
		"world": "Honbra",
		"level": 2373,
		"value": 222290743923
	},
	{
		"rank": 47,
		"name": "Daniloz Corporation",
		"vocation": "Elder Druid",
		"world": "Issobra",
		"level": 2361,
		"value": 218941758427
	},
	{
		"rank": 48,
		"name": "Chronos Poderoso",
		"vocation": "Elder Druid",
		"world": "Unebra",
		"level": 2355,
		"value": 217345827788
	},
	{
		"rank": 49,
		"name": "Megazao Supreme Emex",
		"vocation": "Elder Druid",
		"world": "Havera",
		"level": 2348,
		"value": 215236796423
	},
	{
		"rank": 50,
		"name": "Chris Dictador",
		"vocation": "Royal Paladin",
		"world": "Ombra",
		"level": 2339,
		"value": 212745489524
	},
	{
		"rank": 51,
		"name": "Felix Hastalo Infierno",
		"vocation": "Royal Paladin",
		"world": "Inabra",
		"level": 2337,
		"value": 212377058524
	},
	{
		"rank": 52,
		"name": "Venoox",
		"vocation": "Royal Paladin",
		"world": "Celesta",
		"level": 2336,
		"value": 211976052603
	},
	{
		"rank": 53,
		"name": "Rift Duken",
		"vocation": "Master Sorcerer",
		"world": "Gentebra",
		"level": 2330,
		"value": 210524555171
	},
	{
		"rank": 54,
		"name": "Matari",
		"vocation": "Master Sorcerer",
		"world": "Gentebra",
		"level": 2330,
		"value": 210394104067
	},
	{
		"rank": 55,
		"name": "Sorinzinho",
		"vocation": "Elder Druid",
		"world": "Jadebra",
		"level": 2328,
		"value": 209798325124
	},
	{
		"rank": 56,
		"name": "Majorowa",
		"vocation": "Elite Knight",
		"world": "Karmeya",
		"level": 2320,
		"value": 207748581448
	},
	{
		"rank": 57,
		"name": "Alchemistzin",
		"vocation": "Elite Knight",
		"world": "Quelibra",
		"level": 2314,
		"value": 206214093880
	},
	{
		"rank": 58,
		"name": "Smoothyz",
		"vocation": "Royal Paladin",
		"world": "Kalibra",
		"level": 2312,
		"value": 205649284344
	},
	{
		"rank": 59,
		"name": "Mo rgu",
		"vocation": "Elite Knight",
		"world": "Monza",
		"level": 2302,
		"value": 203016961528
	},
	{
		"rank": 60,
		"name": "Treko",
		"vocation": "Royal Paladin",
		"world": "Gentebra",
		"level": 2296,
		"value": 201240334502
	},
	{
		"rank": 61,
		"name": "Pedrin Impostor",
		"vocation": "Royal Paladin",
		"world": "Jadebra",
		"level": 2291,
		"value": 199907410568
	},
	{
		"rank": 62,
		"name": "Medicaux",
		"vocation": "Elder Druid",
		"world": "Celesta",
		"level": 2290,
		"value": 199828378466
	},
	{
		"rank": 63,
		"name": "Lynuux",
		"vocation": "Elder Druid",
		"world": "Celebra",
		"level": 2285,
		"value": 198386702071
	},
	{
		"rank": 64,
		"name": "Sphere Da Doom",
		"vocation": "Elite Knight",
		"world": "Refugia",
		"level": 2282,
		"value": 197792223963
	},
	{
		"rank": 65,
		"name": "Zecrocz Knight",
		"vocation": "Elite Knight",
		"world": "Yonabra",
		"level": 2281,
		"value": 197516978049
	},
	{
		"rank": 66,
		"name": "Recall Poderoso",
		"vocation": "Royal Paladin",
		"world": "Unebra",
		"level": 2279,
		"value": 196955014175
	},
	{
		"rank": 67,
		"name": "Ven Vi",
		"vocation": "Royal Paladin",
		"world": "Refugia",
		"level": 2279,
		"value": 196947793278
	},
	{
		"rank": 68,
		"name": "Hulk Tacadordebolt",
		"vocation": "Royal Paladin",
		"world": "Venebra",
		"level": 2277,
		"value": 196393526977
	},
	{
		"rank": 69,
		"name": "Ze Cueei",
		"vocation": "Elder Druid",
		"world": "Ourobra",
		"level": 2268,
		"value": 194097678010
	},
	{
		"rank": 70,
		"name": "Brauba",
		"vocation": "Royal Paladin",
		"world": "Ustebra",
		"level": 2256,
		"value": 190869911867
	},
	{
		"rank": 71,
		"name": "Mit Iron",
		"vocation": "Elite Knight",
		"world": "Gentebra",
		"level": 2247,
		"value": 188702470586
	},
	{
		"rank": 72,
		"name": "Zainzao",
		"vocation": "Elder Druid",
		"world": "Collabra",
		"level": 2247,
		"value": 188612201973
	},
	{
		"rank": 73,
		"name": "Magiczny",
		"vocation": "Master Sorcerer",
		"world": "Refugia",
		"level": 2246,
		"value": 188552179702
	},
	{
		"rank": 74,
		"name": "Lunatic Princess",
		"vocation": "Elite Knight",
		"world": "Celesta",
		"level": 2244,
		"value": 188004782788
	},
	{
		"rank": 75,
		"name": "Syriz",
		"vocation": "Master Sorcerer",
		"world": "Thyria",
		"level": 2244,
		"value": 187982776468
	},
	{
		"rank": 76,
		"name": "Ninna Gil",
		"vocation": "Master Sorcerer",
		"world": "Celebra",
		"level": 2242,
		"value": 187400968378
	},
	{
		"rank": 77,
		"name": "King Infinytum",
		"vocation": "Elite Knight",
		"world": "Yonabra",
		"level": 2241,
		"value": 187280891703
	},
	{
		"rank": 78,
		"name": "Tonimm",
		"vocation": "Elder Druid",
		"world": "Jadebra",
		"level": 2240,
		"value": 186896657368
	},
	{
		"rank": 79,
		"name": "Dolerozs",
		"vocation": "Elder Druid",
		"world": "Collabra",
		"level": 2235,
		"value": 185714167367
	},
	{
		"rank": 80,
		"name": "Lelezyn",
		"vocation": "Elder Druid",
		"world": "Yonabra",
		"level": 2233,
		"value": 185212275852
	},
	{
		"rank": 81,
		"name": "Anakurawk Dafalasu",
		"vocation": "Elite Knight",
		"world": "Gentebra",
		"level": 2230,
		"value": 184551358270
	},
	{
		"rank": 82,
		"name": "Bobolocik",
		"vocation": "Master Sorcerer",
		"world": "Celesta",
		"level": 2229,
		"value": 184142606377
	},
	{
		"rank": 83,
		"name": "Knighttt Poderoso",
		"vocation": "Elite Knight",
		"world": "Unebra",
		"level": 2228,
		"value": 184075141314
	},
	{
		"rank": 84,
		"name": "Greamir",
		"vocation": "Master Sorcerer",
		"world": "Celesta",
		"level": 2228,
		"value": 183857058741
	},
	{
		"rank": 85,
		"name": "Rei Bibi",
		"vocation": "Elder Druid",
		"world": "Terribra",
		"level": 2227,
		"value": 183735507307
	},
	{
		"rank": 86,
		"name": "Ndetarovasz",
		"vocation": "Elder Druid",
		"world": "Honbra",
		"level": 2225,
		"value": 183112879094
	},
	{
		"rank": 87,
		"name": "Nightt Gaze",
		"vocation": "Master Sorcerer",
		"world": "Karmeya",
		"level": 2225,
		"value": 183094846337
	},
	{
		"rank": 88,
		"name": "Sorin Emperor",
		"vocation": "Elder Druid",
		"world": "Ourobra",
		"level": 2223,
		"value": 182708006664
	},
	{
		"rank": 89,
		"name": "Zapecao",
		"vocation": "Master Sorcerer",
		"world": "Collabra",
		"level": 2222,
		"value": 182544060227
	},
	{
		"rank": 90,
		"name": "Radizao",
		"vocation": "Elite Knight",
		"world": "Collabra",
		"level": 2222,
		"value": 182478989170
	},
	{
		"rank": 91,
		"name": "Almighty Nova",
		"vocation": "Royal Paladin",
		"world": "Wintera",
		"level": 2217,
		"value": 181162300312
	},
	{
		"rank": 92,
		"name": "Sawano Hiroyuki",
		"vocation": "Royal Paladin",
		"world": "Yonabra",
		"level": 2214,
		"value": 180617844687
	},
	{
		"rank": 93,
		"name": "Fael Fahurr",
		"vocation": "Royal Paladin",
		"world": "Quelibra",
		"level": 2214,
		"value": 180418975416
	},
	{
		"rank": 94,
		"name": "Toxic Es Fiado",
		"vocation": "Elder Druid",
		"world": "Havera",
		"level": 2213,
		"value": 180346257576
	},
	{
		"rank": 95,
		"name": "Arknesz",
		"vocation": "Elite Knight",
		"world": "Venebra",
		"level": 2210,
		"value": 179480720447
	},
	{
		"rank": 96,
		"name": "Edi Paladino",
		"vocation": "Royal Paladin",
		"world": "Honbra",
		"level": 2208,
		"value": 178934050819
	},
	{
		"rank": 97,
		"name": "Zonattookitou Poderoso",
		"vocation": "Master Sorcerer",
		"world": "Unebra",
		"level": 2207,
		"value": 178840411262
	},
	{
		"rank": 98,
		"name": "Dany Ellmagnifico",
		"vocation": "Master Sorcerer",
		"world": "Inabra",
		"level": 2206,
		"value": 178547413219
	},
	{
		"rank": 99,
		"name": "Nott Primetime",
		"vocation": "Royal Paladin",
		"world": "Descubra",
		"level": 2197,
		"value": 176442342066
	},
	{
		"rank": 100,
		"name": "Ellmagnifinho Danynho",
		"vocation": "Royal Paladin",
		"world": "Inabra",
		"level": 2196,
		"value": 176219974304
	},
	{
		"rank": 101,
		"name": "Coh en",
		"vocation": "Master Sorcerer",
		"world": "Yonabra",
		"level": 2196,
		"value": 176111729347
	},
	{
		"rank": 102,
		"name": "Dextro Kogz",
		"vocation": "Master Sorcerer",
		"world": "Monza",
		"level": 2192,
		"value": 175209703267
	},
	{
		"rank": 103,
		"name": "Sage Baw",
		"vocation": "Elder Druid",
		"world": "Belobra",
		"level": 2191,
		"value": 174893761044
	},
	{
		"rank": 104,
		"name": "Sheng",
		"vocation": "Elder Druid",
		"world": "Yonabra",
		"level": 2191,
		"value": 174824685086
	},
	{
		"rank": 105,
		"name": "Diones Machine",
		"vocation": "Elite Knight",
		"world": "Issobra",
		"level": 2187,
		"value": 174013366807
	},
	{
		"rank": 106,
		"name": "Magnifik Danybruxo",
		"vocation": "Elder Druid",
		"world": "Inabra",
		"level": 2187,
		"value": 173878503318
	},
	{
		"rank": 107,
		"name": "Eksman",
		"vocation": "Master Sorcerer",
		"world": "Monza",
		"level": 2186,
		"value": 173637987521
	},
	{
		"rank": 108,
		"name": "Conde Danimax",
		"vocation": "Elite Knight",
		"world": "Inabra",
		"level": 2182,
		"value": 172831820760
	},
	{
		"rank": 109,
		"name": "Rickzher Tank",
		"vocation": "Elite Knight",
		"world": "Issobra",
		"level": 2179,
		"value": 172037576144
	},
	{
		"rank": 110,
		"name": "Guczman",
		"vocation": "Royal Paladin",
		"world": "Monza",
		"level": 2179,
		"value": 172013652486
	},
	{
		"rank": 111,
		"name": "Murilon Hardtimes",
		"vocation": "Elder Druid",
		"world": "Collabra",
		"level": 2179,
		"value": 171987538568
	},
	{
		"rank": 112,
		"name": "Smka Corporation",
		"vocation": "Master Sorcerer",
		"world": "Issobra",
		"level": 2176,
		"value": 171436798651
	},
	{
		"rank": 113,
		"name": "Fernizx",
		"vocation": "Master Sorcerer",
		"world": "Luminera",
		"level": 2172,
		"value": 170473161556
	},
	{
		"rank": 114,
		"name": "Arinth",
		"vocation": "Elite Knight",
		"world": "Monza",
		"level": 2172,
		"value": 170405232254
	},
	{
		"rank": 115,
		"name": "Ahameed",
		"vocation": "Elder Druid",
		"world": "Gentebra",
		"level": 2170,
		"value": 169954478744
	},
	{
		"rank": 116,
		"name": "Fael Outlaw",
		"vocation": "Royal Paladin",
		"world": "Quelibra",
		"level": 2169,
		"value": 169709668124
	},
	{
		"rank": 117,
		"name": "Ximboka Primetime",
		"vocation": "Elder Druid",
		"world": "Venebra",
		"level": 2164,
		"value": 168633140246
	},
	{
		"rank": 118,
		"name": "Shoxiez",
		"vocation": "Master Sorcerer",
		"world": "Kalibra",
		"level": 2163,
		"value": 168260195269
	},
	{
		"rank": 119,
		"name": "Bratku Boy",
		"vocation": "Royal Paladin",
		"world": "Secura",
		"level": 2162,
		"value": 168087319199
	},
	{
		"rank": 120,
		"name": "Hiro Teensina",
		"vocation": "Elder Druid",
		"world": "Gentebra",
		"level": 2162,
		"value": 168058568207
	},
	{
		"rank": 121,
		"name": "Pedrin Orangepodi",
		"vocation": "Elite Knight",
		"world": "Jadebra",
		"level": 2161,
		"value": 167926273875
	},
	{
		"rank": 122,
		"name": "Surufon",
		"vocation": "Elder Druid",
		"world": "Celebra",
		"level": 2159,
		"value": 167370219689
	},
	{
		"rank": 123,
		"name": "He ellz",
		"vocation": "Royal Paladin",
		"world": "Wintera",
		"level": 2156,
		"value": 166608230366
	},
	{
		"rank": 124,
		"name": "Caaok",
		"vocation": "Royal Paladin",
		"world": "Belobra",
		"level": 2151,
		"value": 165552635289
	},
	{
		"rank": 125,
		"name": "Waguinho The Legend",
		"vocation": "Elder Druid",
		"world": "Quelibra",
		"level": 2149,
		"value": 164949752433
	},
	{
		"rank": 126,
		"name": "Mor Decai",
		"vocation": "Master Sorcerer",
		"world": "Gentebra",
		"level": 2148,
		"value": 164865562340
	},
	{
		"rank": 127,
		"name": "Girl Selly",
		"vocation": "Elder Druid",
		"world": "Belobra",
		"level": 2148,
		"value": 164819347050
	},
	{
		"rank": 128,
		"name": "Boysorc",
		"vocation": "Master Sorcerer",
		"world": "Terribra",
		"level": 2147,
		"value": 164684011989
	},
	{
		"rank": 129,
		"name": "Now",
		"vocation": "Royal Paladin",
		"world": "Epoca",
		"level": 2147,
		"value": 164625792885
	},
	{
		"rank": 130,
		"name": "Yunski",
		"vocation": "Royal Paladin",
		"world": "Secura",
		"level": 2147,
		"value": 164510426290
	},
	{
		"rank": 131,
		"name": "Arraya Hardtimes",
		"vocation": "Master Sorcerer",
		"world": "Collabra",
		"level": 2145,
		"value": 164125246421
	},
	{
		"rank": 132,
		"name": "Turco Loko",
		"vocation": "Royal Paladin",
		"world": "Inabra",
		"level": 2144,
		"value": 164008533994
	},
	{
		"rank": 133,
		"name": "Lord Valeta",
		"vocation": "Master Sorcerer",
		"world": "Celebra",
		"level": 2143,
		"value": 163782467635
	},
	{
		"rank": 134,
		"name": "Max Fleury",
		"vocation": "Elite Knight",
		"world": "Celebra",
		"level": 2139,
		"value": 162723147524
	},
	{
		"rank": 135,
		"name": "Goa Santiago",
		"vocation": "Master Sorcerer",
		"world": "Ourobra",
		"level": 2138,
		"value": 162565162363
	},
	{
		"rank": 136,
		"name": "Lutador Shivinha",
		"vocation": "Royal Paladin",
		"world": "Gentebra",
		"level": 2138,
		"value": 162441426550
	},
	{
		"rank": 137,
		"name": "Vitiinn",
		"vocation": "Royal Paladin",
		"world": "Belobra",
		"level": 2136,
		"value": 162000323396
	},
	{
		"rank": 138,
		"name": "Seju Primetime",
		"vocation": "Master Sorcerer",
		"world": "Venebra",
		"level": 2133,
		"value": 161445532246
	},
	{
		"rank": 139,
		"name": "Tonim Sniper",
		"vocation": "Royal Paladin",
		"world": "Jadebra",
		"level": 2132,
		"value": 161173400981
	},
	{
		"rank": 140,
		"name": "Ragnarr Vilao",
		"vocation": "Elite Knight",
		"world": "Ourobra",
		"level": 2129,
		"value": 160549594683
	},
	{
		"rank": 141,
		"name": "Ja co",
		"vocation": "Elite Knight",
		"world": "Refugia",
		"level": 2125,
		"value": 159589216137
	},
	{
		"rank": 142,
		"name": "Xenge Teensina",
		"vocation": "Elite Knight",
		"world": "Gentebra",
		"level": 2124,
		"value": 159375710899
	},
	{
		"rank": 143,
		"name": "Yamaanek",
		"vocation": "Elder Druid",
		"world": "Monza",
		"level": 2123,
		"value": 159189222333
	},
	{
		"rank": 144,
		"name": "Junzaao",
		"vocation": "Master Sorcerer",
		"world": "Belobra",
		"level": 2122,
		"value": 159024715258
	},
	{
		"rank": 145,
		"name": "Hecks Leads",
		"vocation": "Elder Druid",
		"world": "Luminera",
		"level": 2121,
		"value": 158671245271
	},
	{
		"rank": 146,
		"name": "Soiji",
		"vocation": "Elite Knight",
		"world": "Inabra",
		"level": 2121,
		"value": 158587401233
	},
	{
		"rank": 147,
		"name": "Arkelogon",
		"vocation": "Royal Paladin",
		"world": "Celebra",
		"level": 2120,
		"value": 158454210479
	},
	{
		"rank": 148,
		"name": "Chris Zeroum",
		"vocation": "Master Sorcerer",
		"world": "Ombra",
		"level": 2120,
		"value": 158380568176
	},
	{
		"rank": 149,
		"name": "Szmuggy",
		"vocation": "Royal Paladin",
		"world": "Thyria",
		"level": 2120,
		"value": 158373572102
	},
	{
		"rank": 150,
		"name": "Lichtsz",
		"vocation": "Master Sorcerer",
		"world": "Inabra",
		"level": 2119,
		"value": 158268953964
	},
	{
		"rank": 151,
		"name": "Paulox Toxico",
		"vocation": "Royal Paladin",
		"world": "Kalibra",
		"level": 2117,
		"value": 157863068642
	},
	{
		"rank": 152,
		"name": "Estilo Trollzinho",
		"vocation": "Elder Druid",
		"world": "Rasteibra",
		"level": 2116,
		"value": 157656104887
	},
	{
		"rank": 153,
		"name": "Neto Orangepodi",
		"vocation": "Master Sorcerer",
		"world": "Jadebra",
		"level": 2115,
		"value": 157245842787
	},
	{
		"rank": 154,
		"name": "Pulga Doleiro",
		"vocation": "Royal Paladin",
		"world": "Terribra",
		"level": 2114,
		"value": 157169761373
	},
	{
		"rank": 155,
		"name": "Destemido Corporation",
		"vocation": "Royal Paladin",
		"world": "Issobra",
		"level": 2112,
		"value": 156672406550
	},
	{
		"rank": 156,
		"name": "Fraanco",
		"vocation": "Master Sorcerer",
		"world": "Unebra",
		"level": 2111,
		"value": 156383136600
	},
	{
		"rank": 157,
		"name": "Stefan Smakolysz",
		"vocation": "Elite Knight",
		"world": "Bona",
		"level": 2110,
		"value": 156144810846
	},
	{
		"rank": 158,
		"name": "Wrath Saga",
		"vocation": "Elite Knight",
		"world": "Gladera",
		"level": 2109,
		"value": 156076139665
	},
	{
		"rank": 159,
		"name": "Ivene",
		"vocation": "Royal Paladin",
		"world": "Celesta",
		"level": 2109,
		"value": 156064603196
	},
	{
		"rank": 160,
		"name": "Golden Eclypse",
		"vocation": "Royal Paladin",
		"world": "Yonabra",
		"level": 2109,
		"value": 155990106828
	},
	{
		"rank": 161,
		"name": "Vomolu",
		"vocation": "Elite Knight",
		"world": "Celebra",
		"level": 2108,
		"value": 155705992197
	},
	{
		"rank": 162,
		"name": "General Keyllor",
		"vocation": "Elder Druid",
		"world": "Gentebra",
		"level": 2107,
		"value": 155467461167
	},
	{
		"rank": 163,
		"name": "Be xu",
		"vocation": "Elder Druid",
		"world": "Monza",
		"level": 2106,
		"value": 155242767902
	},
	{
		"rank": 164,
		"name": "Maarculino",
		"vocation": "Royal Paladin",
		"world": "Unebra",
		"level": 2105,
		"value": 155149157628
	},
	{
		"rank": 165,
		"name": "Fastshot",
		"vocation": "Royal Paladin",
		"world": "Refugia",
		"level": 2103,
		"value": 154783097129
	},
	{
		"rank": 166,
		"name": "Kalashnkov",
		"vocation": "Royal Paladin",
		"world": "Rasteibra",
		"level": 2103,
		"value": 154748866831
	},
	{
		"rank": 167,
		"name": "Chris Donhodo Ombra",
		"vocation": "Elite Knight",
		"world": "Ombra",
		"level": 2103,
		"value": 154658374280
	},
	{
		"rank": 168,
		"name": "Sorin Enterpriise",
		"vocation": "Royal Paladin",
		"world": "Ourobra",
		"level": 2102,
		"value": 154378967749
	},
	{
		"rank": 169,
		"name": "Pato Zedrin",
		"vocation": "Royal Paladin",
		"world": "Ourobra",
		"level": 2101,
		"value": 154162930760
	},
	{
		"rank": 170,
		"name": "Judgementdays",
		"vocation": "Elder Druid",
		"world": "Calmera",
		"level": 2100,
		"value": 154096787949
	},
	{
		"rank": 171,
		"name": "Camiiss",
		"vocation": "Elder Druid",
		"world": "Kalibra",
		"level": 2098,
		"value": 153638099615
	},
	{
		"rank": 172,
		"name": "Pedrin Feliznatal",
		"vocation": "Royal Paladin",
		"world": "Unebra",
		"level": 2098,
		"value": 153608636319
	},
	{
		"rank": 173,
		"name": "Devzin",
		"vocation": "Royal Paladin",
		"world": "Celesta",
		"level": 2097,
		"value": 153291265313
	},
	{
		"rank": 174,
		"name": "Rodrigaumd",
		"vocation": "Elder Druid",
		"world": "Inabra",
		"level": 2096,
		"value": 153233476431
	},
	{
		"rank": 175,
		"name": "Miichaszek",
		"vocation": "Master Sorcerer",
		"world": "Refugia",
		"level": 2096,
		"value": 153153742764
	},
	{
		"rank": 176,
		"name": "Rexiruz Zabojca",
		"vocation": "Master Sorcerer",
		"world": "Terribra",
		"level": 2095,
		"value": 152973284440
	},
	{
		"rank": 177,
		"name": "Jazh",
		"vocation": "Elder Druid",
		"world": "Venebra",
		"level": 2093,
		"value": 152535983618
	},
	{
		"rank": 178,
		"name": "Lowdaz",
		"vocation": "Royal Paladin",
		"world": "Monstera",
		"level": 2092,
		"value": 152309087782
	},
	{
		"rank": 179,
		"name": "Rafittzz",
		"vocation": "Master Sorcerer",
		"world": "Belobra",
		"level": 2092,
		"value": 152303453141
	},
	{
		"rank": 180,
		"name": "Rdge",
		"vocation": "Master Sorcerer",
		"world": "Yonabra",
		"level": 2091,
		"value": 152021033503
	},
	{
		"rank": 181,
		"name": "Vyvy",
		"vocation": "Master Sorcerer",
		"world": "Calmera",
		"level": 2091,
		"value": 152007489522
	},
	{
		"rank": 182,
		"name": "Figolo",
		"vocation": "Elite Knight",
		"world": "Monza",
		"level": 2089,
		"value": 151592532800
	},
	{
		"rank": 183,
		"name": "Icarus Cltcansado",
		"vocation": "Master Sorcerer",
		"world": "Ourobra",
		"level": 2089,
		"value": 151580718621
	},
	{
		"rank": 184,
		"name": "Halzor Megalomaniaco",
		"vocation": "Elite Knight",
		"world": "Kalibra",
		"level": 2085,
		"value": 150708336991
	},
	{
		"rank": 185,
		"name": "Vyp Fox",
		"vocation": "Master Sorcerer",
		"world": "Gentebra",
		"level": 2083,
		"value": 150267425179
	},
	{
		"rank": 186,
		"name": "Czikita",
		"vocation": "Elder Druid",
		"world": "Secura",
		"level": 2083,
		"value": 150264633167
	},
	{
		"rank": 187,
		"name": "Wakii Szef",
		"vocation": "Elite Knight",
		"world": "Celesta",
		"level": 2083,
		"value": 150214033091
	},
	{
		"rank": 188,
		"name": "Verfix",
		"vocation": "Elder Druid",
		"world": "Ustebra",
		"level": 2082,
		"value": 150128898078
	},
	{
		"rank": 189,
		"name": "Owbapzera",
		"vocation": "Royal Paladin",
		"world": "Descubra",
		"level": 2080,
		"value": 149732868023
	},
	{
		"rank": 190,
		"name": "Toxic Ghost Esecee",
		"vocation": "Master Sorcerer",
		"world": "Havera",
		"level": 2079,
		"value": 149371062744
	},
	{
		"rank": 191,
		"name": "Dzwoni Daro",
		"vocation": "Elder Druid",
		"world": "Monza",
		"level": 2078,
		"value": 149313841021
	},
	{
		"rank": 192,
		"name": "Ranny Zolnierz Elder",
		"vocation": "Master Sorcerer",
		"world": "Antica",
		"level": 2078,
		"value": 149229363122
	},
	{
		"rank": 193,
		"name": "Rei Tarik",
		"vocation": "Elite Knight",
		"world": "Terribra",
		"level": 2078,
		"value": 149159104475
	},
	{
		"rank": 194,
		"name": "Trullen",
		"vocation": "Elder Druid",
		"world": "Celesta",
		"level": 2077,
		"value": 148932548593
	},
	{
		"rank": 195,
		"name": "Zezinho Eurofeer",
		"vocation": "Elite Knight",
		"world": "Ourobra",
		"level": 2076,
		"value": 148890903617
	},
	{
		"rank": 196,
		"name": "Destructive Kronun",
		"vocation": "Elite Knight",
		"world": "Talera",
		"level": 2076,
		"value": 148849949671
	},
	{
		"rank": 197,
		"name": "Mattwin",
		"vocation": "Elder Druid",
		"world": "Venebra",
		"level": 2075,
		"value": 148608335694
	},
	{
		"rank": 198,
		"name": "Kallashy",
		"vocation": "Elite Knight",
		"world": "Honbra",
		"level": 2075,
		"value": 148513704063
	},
	{
		"rank": 199,
		"name": "Kewhyx Mythus",
		"vocation": "Royal Paladin",
		"world": "Celebra",
		"level": 2074,
		"value": 148343822495
	},
	{
		"rank": 200,
		"name": "Ezudux",
		"vocation": "Royal Paladin",
		"world": "Gentebra",
		"level": 2072,
		"value": 147988158578
	},
	{
		"rank": 201,
		"name": "Cloud Cronos",
		"vocation": "Elder Druid",
		"world": "Harmonia",
		"level": 2070,
		"value": 147445729150
	},
	{
		"rank": 202,
		"name": "Duzy Brzuszek",
		"vocation": "Master Sorcerer",
		"world": "Nevia",
		"level": 2069,
		"value": 147228105926
	},
	{
		"rank": 203,
		"name": "Alpha Charly",
		"vocation": "Royal Paladin",
		"world": "Gentebra",
		"level": 2068,
		"value": 147112224942
	},
	{
		"rank": 204,
		"name": "Axbin",
		"vocation": "Master Sorcerer",
		"world": "Astera",
		"level": 2068,
		"value": 147083209640
	},
	{
		"rank": 205,
		"name": "Rodrigaaum",
		"vocation": "Royal Paladin",
		"world": "Inabra",
		"level": 2066,
		"value": 146722150103
	},
	{
		"rank": 206,
		"name": "Mighty Peral",
		"vocation": "Elder Druid",
		"world": "Solidera",
		"level": 2064,
		"value": 146196218965
	},
	{
		"rank": 207,
		"name": "Zwkidek",
		"vocation": "Elite Knight",
		"world": "Gentebra",
		"level": 2064,
		"value": 146195846985
	},
	{
		"rank": 208,
		"name": "Ginowi",
		"vocation": "Royal Paladin",
		"world": "Monza",
		"level": 2063,
		"value": 146013377556
	},
	{
		"rank": 209,
		"name": "Amora Enterprise",
		"vocation": "Elite Knight",
		"world": "Ourobra",
		"level": 2061,
		"value": 145644821011
	},
	{
		"rank": 210,
		"name": "Arc Mago Marujo",
		"vocation": "Master Sorcerer",
		"world": "Serdebra",
		"level": 2060,
		"value": 145361956254
	},
	{
		"rank": 211,
		"name": "Zeeh Chinelo",
		"vocation": "Master Sorcerer",
		"world": "Celebra",
		"level": 2059,
		"value": 145110500198
	},
	{
		"rank": 212,
		"name": "Pedrin Aposentado",
		"vocation": "Master Sorcerer",
		"world": "Jadebra",
		"level": 2058,
		"value": 145008499338
	},
	{
		"rank": 213,
		"name": "Barao Relampejante",
		"vocation": "Elite Knight",
		"world": "Yonabra",
		"level": 2058,
		"value": 144954065442
	},
	{
		"rank": 214,
		"name": "Zonaattokitou Poderoso",
		"vocation": "Elder Druid",
		"world": "Unebra",
		"level": 2057,
		"value": 144802787179
	},
	{
		"rank": 215,
		"name": "Trakhinas",
		"vocation": "Royal Paladin",
		"world": "Quelibra",
		"level": 2054,
		"value": 144078966398
	},
	{
		"rank": 216,
		"name": "Thor Zynz",
		"vocation": "Royal Paladin",
		"world": "Collabra",
		"level": 2053,
		"value": 143895939519
	},
	{
		"rank": 217,
		"name": "Vine Corporation",
		"vocation": "Elder Druid",
		"world": "Etebra",
		"level": 2052,
		"value": 143711161895
	},
	{
		"rank": 218,
		"name": "Luidao Inevitavel",
		"vocation": "Elder Druid",
		"world": "Ourobra",
		"level": 2051,
		"value": 143376937166
	},
	{
		"rank": 219,
		"name": "Partyboost",
		"vocation": "Royal Paladin",
		"world": "Vunira",
		"level": 2050,
		"value": 143223572575
	},
	{
		"rank": 220,
		"name": "Dan Senju",
		"vocation": "Royal Paladin",
		"world": "Collabra",
		"level": 2049,
		"value": 143105687073
	},
	{
		"rank": 221,
		"name": "Legends Of Dante",
		"vocation": "Elder Druid",
		"world": "Oceanis",
		"level": 2047,
		"value": 142621196562
	},
	{
		"rank": 222,
		"name": "Intenzao Supreme Emex",
		"vocation": "Master Sorcerer",
		"world": "Havera",
		"level": 2046,
		"value": 142435549357
	},
	{
		"rank": 223,
		"name": "Lightbinder",
		"vocation": "Royal Paladin",
		"world": "Secura",
		"level": 2046,
		"value": 142434924571
	},
	{
		"rank": 224,
		"name": "Magnifik Danytank",
		"vocation": "Elite Knight",
		"world": "Quelibra",
		"level": 2045,
		"value": 142298313481
	},
	{
		"rank": 225,
		"name": "Max Namikaze",
		"vocation": "Elder Druid",
		"world": "Collabra",
		"level": 2045,
		"value": 142260862607
	},
	{
		"rank": 226,
		"name": "Captain Gufi",
		"vocation": "Elder Druid",
		"world": "Refugia",
		"level": 2043,
		"value": 141771483140
	},
	{
		"rank": 227,
		"name": "Surkkaam",
		"vocation": "Elder Druid",
		"world": "Bona",
		"level": 2043,
		"value": 141703603454
	},
	{
		"rank": 228,
		"name": "Sinfronio Stark",
		"vocation": "Elder Druid",
		"world": "Rasteibra",
		"level": 2041,
		"value": 141396737562
	},
	{
		"rank": 229,
		"name": "Maza lov",
		"vocation": "Master Sorcerer",
		"world": "Ourobra",
		"level": 2040,
		"value": 141153988702
	},
	{
		"rank": 230,
		"name": "Angel Pro Damage",
		"vocation": "Elder Druid",
		"world": "Yonabra",
		"level": 2040,
		"value": 141094136874
	},
	{
		"rank": 231,
		"name": "Yoasobi",
		"vocation": "Master Sorcerer",
		"world": "Yonabra",
		"level": 2038,
		"value": 140870436728
	},
	{
		"rank": 232,
		"name": "Luke no San",
		"vocation": "Royal Paladin",
		"world": "Collabra",
		"level": 2037,
		"value": 140565760667
	},
	{
		"rank": 233,
		"name": "Leozinnxd",
		"vocation": "Master Sorcerer",
		"world": "Rasteibra",
		"level": 2035,
		"value": 140043564150
	},
	{
		"rank": 234,
		"name": "Evilnesz",
		"vocation": "Royal Paladin",
		"world": "Venebra",
		"level": 2034,
		"value": 140014219868
	},
	{
		"rank": 235,
		"name": "Dudu Stonecutter",
		"vocation": "Elite Knight",
		"world": "Unebra",
		"level": 2034,
		"value": 139906931692
	},
	{
		"rank": 236,
		"name": "Nyghtz",
		"vocation": "Royal Paladin",
		"world": "Yonabra",
		"level": 2030,
		"value": 139056481282
	},
	{
		"rank": 237,
		"name": "Kuubiq",
		"vocation": "Royal Paladin",
		"world": "Thyria",
		"level": 2029,
		"value": 138948287224
	},
	{
		"rank": 238,
		"name": "Kairos Skylight",
		"vocation": "Elite Knight",
		"world": "Calmera",
		"level": 2029,
		"value": 138895769641
	},
	{
		"rank": 239,
		"name": "Murillaoloko",
		"vocation": "Master Sorcerer",
		"world": "Quelibra",
		"level": 2029,
		"value": 138866542193
	},
	{
		"rank": 240,
		"name": "Mantessa",
		"vocation": "Master Sorcerer",
		"world": "Refugia",
		"level": 2028,
		"value": 138697107850
	},
	{
		"rank": 241,
		"name": "Lutador de Mace",
		"vocation": "Elite Knight",
		"world": "Gentebra",
		"level": 2028,
		"value": 138649805577
	},
	{
		"rank": 242,
		"name": "Naruciaczek",
		"vocation": "Royal Paladin",
		"world": "Celesta",
		"level": 2027,
		"value": 138570713328
	},
	{
		"rank": 243,
		"name": "Heyz zerp",
		"vocation": "Royal Paladin",
		"world": "Inabra",
		"level": 2027,
		"value": 138439809943
	},
	{
		"rank": 244,
		"name": "Zezinho Ltda",
		"vocation": "Elder Druid",
		"world": "Ourobra",
		"level": 2026,
		"value": 138365227181
	},
	{
		"rank": 245,
		"name": "Marco letta",
		"vocation": "Elite Knight",
		"world": "Ourobra",
		"level": 2023,
		"value": 137676125880
	},
	{
		"rank": 246,
		"name": "Deadmani",
		"vocation": "Elite Knight",
		"world": "Thyria",
		"level": 2022,
		"value": 137450864768
	},
	{
		"rank": 247,
		"name": "Sedrahil",
		"vocation": "Royal Paladin",
		"world": "Oceanis",
		"level": 2022,
		"value": 137437014018
	},
	{
		"rank": 248,
		"name": "Ragha Healer",
		"vocation": "Elder Druid",
		"world": "Kalibra",
		"level": 2022,
		"value": 137387959310
	},
	{
		"rank": 249,
		"name": "Mirotth",
		"vocation": "Elite Knight",
		"world": "Belobra",
		"level": 2021,
		"value": 137276692444
	},
	{
		"rank": 250,
		"name": "Lutador Venancinho",
		"vocation": "Master Sorcerer",
		"world": "Gentebra",
		"level": 2021,
		"value": 137245175608
	}
]
